NeuLogPy/NeuLog.py
NeuLogPy/__init__.py
NeuLogPy/config/__init__.py
NeuLogPy/core/__init__.py
NeuLogPy/core/api_client.py
NeuLogPy/core/experiment.py
NeuLogPy/core/logger.py
NeuLogPy/core/sensor_registry.py
NeuLogPy/models/__init__.py
NeuLogPy/models/sensor.py
NeuLogPy/tests/__init__.py
NeuLogPy/tests/test_sensor_registry.py
NeuLogPy/utils/__init__.py
NeuLogPy/utils/file_loader.py
NeuLogPy-1.4.0.dist-info/METADATA
NeuLogPy-1.4.0.dist-info/WHEEL
NeuLogPy-1.4.0.dist-info/entry_points.txt
NeuLogPy-1.4.0.dist-info/top_level.txt
NeuLogPy-1.4.0.dist-info/RECORD
