Metadata-Version: 2.1
Name: NeuLogPy
Version: 1.4.0
Summary: Python interface for NeuLog sensors with real-time visualization
Home-page: https://github.com/sustronics/neulogpy
Author: Sustronics
Author-email: info@sustronics.com
Classifier: Development Status :: 4 - Beta
Classifier: Intended Audience :: Science/Research
Classifier: License :: OSI Approved :: MIT License
Classifier: Programming Language :: Python :: 3
Classifier: Programming Language :: Python :: 3.7
Classifier: Programming Language :: Python :: 3.8
Classifier: Programming Language :: Python :: 3.9
Classifier: Programming Language :: Python :: 3.10
Classifier: Programming Language :: Python :: 3.11
Classifier: Topic :: Scientific/Engineering :: Visualization
Classifier: Topic :: Scientific/Engineering :: Medical Science Apps.
Requires-Python: >=3.7
Requires-Dist: pydantic>=2.0.0
Requires-Dist: requests>=2.25.0
Requires-Dist: pyyaml>=5.4.0
Requires-Dist: dearpygui>=1.9.0
